customer_report/__init__.py
customer_report/customer_report.py
invest_calc/__init__.py
invest_calc/fin_calc.py
order_receipt/__init__.py
order_receipt/order_receipt.py
sales_report/__init__.py
sales_report/sales_report.py
transaction_report/__init__.py
transaction_report/transaction_report.py
customer_report-0.1.0.dist-info/METADATA
customer_report-0.1.0.dist-info/WHEEL
customer_report-0.1.0.dist-info/top_level.txt
customer_report-0.1.0.dist-info/RECORD
