Metadata-Version: 2.1
Name: customer_report
Version: 0.1.0
Summary: Пакет для cоздания отчёта о клиентах
Author-email: mikhail <m.zimin@edu.centraluniversity.ru>
Requires-Dist: argparse
